aes128/__init__.py
aes128/aes128.py
aes128_NAB-0.0.2.dist-info/LICENSE
aes128_NAB-0.0.2.dist-info/METADATA
aes128_NAB-0.0.2.dist-info/WHEEL
aes128_NAB-0.0.2.dist-info/top_level.txt
aes128_NAB-0.0.2.dist-info/RECORD
