Metadata-Version: 2.1
Name: aes128-NAB
Version: 0.0.2
Summary: encrypt decrypt password using aes 128.
Author-email: ABOULOIFA Najib <najib.abouloifa@gmail.com>
Project-URL: Homepage, https://github.com/ABNajib
Project-URL: Bug Tracker, https://github.com/ABNajib
Classifier: Programming Language :: Python :: 3
Classifier: License :: OSI Approved :: MIT License
Classifier: Operating System :: OS Independent
Requires-Python: >=3.7
License-File: LICENSE
